ampy_bus-1.2.0.dist-info/licenses/LICENSE
ampybus/__init__.py
ampybus/_version.py
ampybus/codec.py
ampybus/envelope.py
ampybus/headers.py
ampybus/metrics.py
ampybus/nats_bus.py
ampybus/otel.py
ampybus/schemahash.py
ampybus/trace.py
examples/py_dlq_inspect.py
examples/py_dlq_redrive.py
examples/py_nats_pub.py
examples/py_nats_sub.py
examples/py_send_poison.py
examples/simple_roundtrip.py
tests/conftest.py
tests/test_ampy_proto_compat.py
tests/test_roundtrip.py
tests/test_schemahash.py
ampy_bus-1.2.0.dist-info/METADATA
ampy_bus-1.2.0.dist-info/WHEEL
ampy_bus-1.2.0.dist-info/top_level.txt
ampy_bus-1.2.0.dist-info/RECORD
